{"version":2,"features":[{"name":"OilResource","id":1304,"position":[2496,1216],"rotation":32768},{"name":"OilResource","id":958,"position":[960,19264],"rotation":0},{"name":"OilResource","id":975,"position":[1728,19648],"rotation":0},{"name":"OilResource","id":1302,"position":[1216,960],"rotation":32768},{"name":"OilResource","id":1305,"position":[1344,832],"rotation":32768},{"name":"OilResource","id":1288,"position":[960,832],"rotation":32768},{"name":"OilResource","id":1287,"position":[1344,960],"rotation":32768},{"name":"OilResource","id":1272,"position":[832,1216],"rotation":32768},{"name":"OilResource","id":1274,"position":[1728,832],"rotation":32768},{"name":"OilResource","id":1298,"position":[2496,1344],"rotation":32768},{"name":"OilResource","id":981,"position":[2496,19648],"rotation":0},{"name":"OilResource","id":969,"position":[2368,19520],"rotation":0},{"name":"OilResource","id":984,"position":[2368,19264],"rotation":0},{"name":"OilResource","id":963,"position":[1216,19136],"rotation":0},{"name":"OilResource","id":957,"position":[832,19648],"rotation":0},{"name":"OilResource","id":1284,"position":[2496,832],"rotation":32768},{"name":"OilResource","id":978,"position":[1600,19520],"rotation":0},{"name":"OilResource","id":1301,"position":[2368,1216],"rotation":32768},{"name":"OilResource","id":965,"position":[1984,19520],"rotation":0},{"name":"OilResource","id":1285,"position":[960,1216],"rotation":32768},{"name":"OilResource","id":1281,"position":[2112,1344],"rotation":32768},{"name":"OilResource","id":1310,"position":[1344,1344],"rotation":32768},{"name":"OilResource","id":1296,"position":[2368,832],"rotation":32768},{"name":"OilResource","id":983,"position":[1984,19648],"rotation":0},{"name":"OilResource","id":1283,"position":[2368,960],"rotation":32768},{"name":"OilResource","id":962,"position":[960,19136],"rotation":0},{"name":"OilResource","id":964,"position":[960,19648],"rotation":0},{"name":"OilResource","id":977,"position":[2496,19264],"rotation":0},{"name":"OilResource","id":1300,"position":[1216,1344],"rotation":32768},{"name":"OilResource","id":979,"position":[1984,19136],"rotation":0},{"name":"OilResource","id":980,"position":[1728,19520],"rotation":0},{"name":"OilResource","id":966,"position":[1216,19648],"rotation":0},{"name":"OilResource","id":968,"position":[2368,19136],"rotation":0},{"name":"OilResource","id":961,"position":[832,19520],"rotation":0},{"name":"OilResource","id":991,"position":[1728,19136],"rotation":0},{"name":"OilResource","id":989,"position":[1216,19520],"rotation":0},{"name":"OilResource","id":985,"position":[1216,19264],"rotation":0},{"name":"OilResource","id":990,"position":[2496,19136],"rotation":0},{"name":"OilResource","id":956,"position":[832,19136],"rotation":0},{"name":"OilResource","id":992,"position":[2112,19648],"rotation":0},{"name":"OilResource","id":971,"position":[2112,19520],"rotation":0},{"name":"OilResource","id":988,"position":[832,19264],"rotation":0},{"name":"OilResource","id":993,"position":[2496,19520],"rotation":0},{"name":"OilResource","id":994,"position":[2112,19264],"rotation":0},{"name":"OilResource","id":973,"position":[960,19520],"rotation":0},{"name":"OilResource","id":1295,"position":[960,1344],"rotation":32768},{"name":"OilResource","id":1291,"position":[1728,1216],"rotation":32768},{"name":"OilResource","id":1280,"position":[1984,1344],"rotation":32768},{"name":"OilResource","id":1290,"position":[1600,1344],"rotation":32768},{"name":"OilResource","id":1293,"position":[832,832],"rotation":32768},{"name":"OilResource","id":1292,"position":[1216,1216],"rotation":32768},{"name":"OilResource","id":1308,"position":[1216,832],"rotation":32768},{"name":"OilResource","id":1299,"position":[1728,960],"rotation":32768},{"name":"OilResource","id":1276,"position":[1728,1344],"rotation":32768},{"name":"OilResource","id":1303,"position":[2112,832],"rotation":32768},{"name":"OilResource","id":960,"position":[1344,19520],"rotation":0},{"name":"OilResource","id":986,"position":[1344,19648],"rotation":0},{"name":"OilResource","id":1282,"position":[1984,832],"rotation":32768},{"name":"OilResource","id":982,"position":[1600,19136],"rotation":0},{"name":"OilResource","id":955,"position":[1600,19264],"rotation":0},{"name":"OilResource","id":967,"position":[1344,19264],"rotation":0},{"name":"OilResource","id":970,"position":[1600,19648],"rotation":0},{"name":"OilResource","id":976,"position":[2112,19136],"rotation":0},{"name":"OilResource","id":1275,"position":[1984,1216],"rotation":32768},{"name":"OilResource","id":1309,"position":[2496,960],"rotation":32768},{"name":"OilResource","id":1273,"position":[1344,1216],"rotation":32768},{"name":"OilResource","id":1277,"position":[960,960],"rotation":32768},{"name":"OilResource","id":1294,"position":[2112,960],"rotation":32768},{"name":"OilResource","id":1297,"position":[1600,1216],"rotation":32768},{"name":"OilResource","id":1289,"position":[832,1344],"rotation":32768},{"name":"OilResource","id":1158,"position":[832,960],"rotation":32768},{"name":"OilResource","id":1279,"position":[1984,960],"rotation":32768},{"name":"OilResource","id":1286,"position":[1600,832],"rotation":32768},{"name":"OilResource","id":1306,"position":[1600,960],"rotation":32768},{"name":"OilResource","id":959,"position":[1728,19264],"rotation":0},{"name":"OilResource","id":1307,"position":[2112,1216],"rotation":32768},{"name":"OilResource","id":987,"position":[1984,19264],"rotation":0},{"name":"OilResource","id":1278,"position":[2368,1344],"rotation":32768},{"name":"OilResource","id":972,"position":[1344,19136],"rotation":0},{"name":"OilResource","id":974,"position":[2368,19648],"rotation":0}]}