{"version":2,"droids":[{"template":"ConstructionDroid","id":328,"position":[3648,2240],"rotation":0,"startpos":0},{"template":"ConstructionDroid","id":331,"position":[4032,2240],"rotation":0,"startpos":0},{"template":"ConstructionDroid","id":330,"position":[3904,2240],"rotation":0,"startpos":0},{"template":"ConstructionDroid","id":329,"position":[3776,2240],"rotation":0,"startpos":0},{"template":"ConstructionDroid","id":311,"position":[17216,22208],"rotation":0,"startpos":1},{"template":"ConstructionDroid","id":312,"position":[17344,22208],"rotation":0,"startpos":1},{"template":"ConstructionDroid","id":313,"position":[17472,22208],"rotation":0,"startpos":1},{"template":"ConstructionDroid","id":314,"position":[17600,22208],"rotation":0,"startpos":1}]}